{
  "appPageId" : "9af302ba-60fd-4432-bb14-5566e074d711",
  "componentName" : "siteforce:dynamicLayout",
  "dataProviders" : [ ],
  "id" : "44665680-5ac8-4276-abab-6ffb53579583",
  "label" : "My Account",
  "regions" : [ {
    "id" : "c65077d6-d626-4e89-91d0-ebfba01d194e",
    "regionName" : "header",
    "type" : "region"
  }, {
    "components" : [ {
      "componentAttributes" : {
        "background" : "background: rgba(0,0,0,0)",
        "backgroundOverlay" : "rgba(0,0,0,0.5)",
        "contentAreaWidth" : 100,
        "sectionConfig" : {
          "UUID" : "1a1699e9-1cab-4e8e-b735-20cec3ef2f6d",
          "columns" : [ {
            "UUID" : "755a56b3-2584-423f-89a6-afc64b5300e6",
            "columnKey" : "col1",
            "columnName" : "column 1",
            "columnWidth" : "12",
            "seedComponents" : [ {
              "attributes" : {
                "recordId" : "{!CurrentUser.accountId}",
                "sfdc:identifier" : "forceCommunity_recordHeadline"
              },
              "fqn" : "forceCommunity:recordHeadline"
            }, {
              "attributes" : {
                "recordId" : "{!CurrentUser.accountId}",
                "sfdc:identifier" : "forceCommunity_recordHomeTabs"
              },
              "fqn" : "forceCommunity:recordHomeTabs"
            } ]
          } ]
        },
        "sectionHeight" : 32
      },
      "componentName" : "forceCommunity:section",
      "id" : "1a1699e9-1cab-4e8e-b735-20cec3ef2f6d",
      "regions" : [ {
        "components" : [ {
          "componentAttributes" : {
            "recordId" : "{!CurrentUser.accountId}"
          },
          "componentName" : "forceCommunity:recordHeadline",
          "id" : "335b8bfb-dc2e-4096-9702-5dcdaeed8575",
          "renderPriority" : "NEUTRAL",
          "renditionMap" : { },
          "type" : "component"
        }, {
          "componentAttributes" : {
            "detailsTabLabel" : "Details",
            "discussionsTabLabel" : "Feed",
            "recordId" : "{!CurrentUser.accountId}",
            "relatedTabLabel" : "Related",
            "tab1Type" : "details",
            "tab2Type" : "related",
            "tab3Type" : "chatter",
            "tab4Type" : "none",
            "timelineTabLabel" : "Activity"
          },
          "componentName" : "forceCommunity:recordHomeTabs",
          "id" : "c096344d-1793-47a8-a616-b44f3c0e017a",
          "renderPriority" : "NEUTRAL",
          "renditionMap" : { },
          "type" : "component"
        } ],
        "id" : "755a56b3-2584-423f-89a6-afc64b5300e6",
        "regionLabel" : "column 1",
        "regionName" : "col1",
        "renditionMap" : { },
        "type" : "region"
      } ],
      "renderPriority" : "NEUTRAL",
      "renditionMap" : { },
      "type" : "component"
    } ],
    "id" : "0796de39-4f36-4c03-be02-7c7baf4f4a18",
    "regionName" : "content",
    "type" : "region"
  }, {
    "id" : "4da8f376-81f2-4a61-b54c-f8d544ae2af5",
    "regionName" : "footer",
    "type" : "region"
  } ],
  "themeLayoutType" : "Inner",
  "type" : "view",
  "viewType" : "my-account"
}